prawoauth2/PrawOAuth2Mini.py
prawoauth2/PrawOAuth2Server.py
prawoauth2/__init__.py
prawoauth2-0.3.dist-info/DESCRIPTION.rst
prawoauth2-0.3.dist-info/METADATA
prawoauth2-0.3.dist-info/RECORD
prawoauth2-0.3.dist-info/WHEEL
prawoauth2-0.3.dist-info/metadata.json
prawoauth2-0.3.dist-info/pbr.json
prawoauth2-0.3.dist-info/top_level.txt
tests/__init__.py
tests/test_oauth_mini.py
